__init__.py
alpha_chick-0.1.0.dist-info/licenses/LICENSE
tech_indicators/__init__.py
tech_indicators/rsi.py
alpha_chick-0.1.0.dist-info/METADATA
alpha_chick-0.1.0.dist-info/WHEEL
alpha_chick-0.1.0.dist-info/top_level.txt
alpha_chick-0.1.0.dist-info/RECORD
