Metadata-Version: 2.4
Name: alpha-chick
Version: 0.1.0
Summary: High-performance TA indicators for Python
Requires-Python: >=3.12
License-File: LICENSE
Requires-Dist: numpy>=2.3.2
Requires-Dist: pandas>=2.3.1
Dynamic: license-file
